flexsrc/__init__.py
flexsrc/filecontainer.py
flexsrc/flexsrc.py
flexsrc/utils.py
flexsrc-0.1.11.dist-info/METADATA
flexsrc-0.1.11.dist-info/WHEEL
flexsrc-0.1.11.dist-info/top_level.txt
flexsrc-0.1.11.dist-info/RECORD
